{
    "Id": 10521,
    "Question": "which president of the us was first to belong to the republican party",
    "Temporal signal": [
        "ORDINAL"
    ],
    "Temporal question type": [
        "Ordinal"
    ],
    "Answer": [
        {
            "AnswerType": "Entity",
            "WikidataQid": "Q91",
            "WikidataLabel": "Abraham Lincoln",
            "WikipediaURL": "https://en.wikipedia.org/wiki/abraham_lincoln"
        }
    ],
    "Data set": "development",
    "Question truecase": "Which president of the us was first to belong to the Republican party?",
    "Seed entity": [
        {
            "label": "President of the United States",
            "url": "http://www.wikidata.org/entity/Q11696",
            "qid": "Q11696",
            "text": "president",
            "method": "ELQ and TAGME"
        },
        {
            "label": "Republican Party",
            "url": "http://www.wikidata.org/entity/Q29468",
            "qid": "Q29468",
            "text": "republican party",
            "method": "ELQ and TAGME"
        },
        {
            "label": "United States",
            "url": "http://www.wikidata.org/entity/Q30",
            "qid": "Q30",
            "text": "us",
            "method": "ELQ"
        },
        {
            "label": "Belong",
            "url": "http://www.wikidata.org/entity/Q4884518",
            "qid": "Q4884518",
            "text": "belong",
            "method": "TAGME"
        },
        {
            "label": "First Amendment to the United States Constitution",
            "url": "http://www.wikidata.org/entity/Q12616",
            "qid": "Q12616",
            "text": "first",
            "method": "TAGME"
        }
    ],
    "Top5 answer": [
        {
            "rank": 1,
            "label": "Abraham Lincoln",
            "url": "http://www.wikidata.org/entity/Q91",
            "qid": "Q91"
        },
        {
            "rank": 2,
            "label": "George Washington",
            "url": "http://www.wikidata.org/entity/Q23",
            "qid": "Q23"
        },
        {
            "rank": 3,
            "label": "Franklin D. Roosevelt",
            "url": "http://www.wikidata.org/entity/Q8007",
            "qid": "Q8007"
        },
        {
            "rank": 4,
            "label": "William Henry Harrison",
            "url": "http://www.wikidata.org/entity/Q11869",
            "qid": "Q11869"
        },
        {
            "rank": 5,
            "label": "Barack Obama",
            "url": "http://www.wikidata.org/entity/Q76",
            "qid": "Q76"
        }
    ]
}