{
    "Id": 11307,
    "Question": "what is the administrative body of chihuahua that was twinned",
    "Temporal signal": [
        "START"
    ],
    "Temporal question type": [
        "Explicit"
    ],
    "Answer": [
        {
            "AnswerType": "Entity",
            "WikidataQid": "Q34804",
            "WikidataLabel": "Albuquerque",
            "WikipediaURL": "https://en.wikipedia.org/wiki/Albuquerque,_New_Mexico"
        }
    ],
    "Data set": "development",
    "Question truecase": "What is the administrative body of Chihuahua that was twinned?",
    "Seed entity": [
        {
            "label": "Chihuahua",
            "url": "http://www.wikidata.org/entity/Q655",
            "qid": "Q655",
            "text": "chihuahua",
            "method": "ELQ"
        },
        {
            "label": "twin town",
            "url": "http://www.wikidata.org/entity/Q184711",
            "qid": "Q184711",
            "text": "twinned",
            "method": "ELQ and TAGME"
        },
        {
            "label": "Business economics",
            "url": "http://www.wikidata.org/entity/Q2043282",
            "qid": "Q2043282",
            "text": "administrative body",
            "method": "TAGME"
        },
        {
            "label": "Chihuahua",
            "url": "http://www.wikidata.org/entity/Q61302",
            "qid": "Q61302",
            "text": "chihuahua",
            "method": "TAGME"
        }
    ],
    "Top5 answer": [
        {
            "rank": 1,
            "label": "Albuquerque",
            "url": "http://www.wikidata.org/entity/Q34804",
            "qid": "Q34804"
        },
        {
            "rank": 2,
            "label": "Torreón",
            "url": "http://www.wikidata.org/entity/Q386991",
            "qid": "Q386991"
        },
        {
            "rank": 3,
            "label": "Nashville, Tennessee",
            "url": "http://www.wikidata.org/entity/Q23197",
            "qid": "Q23197"
        },
        {
            "rank": 4,
            "label": "Chihuahua",
            "url": "http://www.wikidata.org/entity/Q61302",
            "qid": "Q61302"
        },
        {
            "rank": 5,
            "label": "investigator",
            "url": "http://www.wikidata.org/entity/Q30093123",
            "qid": "Q30093123"
        }
    ]
}