{
    "Id": 11376,
    "Question": "what year what the inflation rate in tonga 10.7",
    "Temporal signal": [
        "No signal"
    ],
    "Temporal question type": [
        "Temp.Ans"
    ],
    "Answer": [
        {
            "AnswerType": "Value",
            "AnswerArgument": "2001-01-01T00:00:00Z"
        }
    ],
    "Data set": "development",
    "Question truecase": "What year what the inflation rate in Tonga 10.7?",
    "Seed entity": [
        {
            "label": "Tonga",
            "url": "http://www.wikidata.org/entity/Q678",
            "qid": "Q678",
            "text": "tonga",
            "method": "ELQ and TAGME"
        },
        {
            "label": "inflation",
            "url": "http://www.wikidata.org/entity/Q35865",
            "qid": "Q35865",
            "text": "inflation rate",
            "method": "ELQ"
        },
        {
            "label": "What a Year",
            "url": "http://www.wikidata.org/entity/Q16967243",
            "qid": "Q16967243",
            "text": "what year",
            "method": "TAGME"
        },
        {
            "label": "What The--?!",
            "url": "http://www.wikidata.org/entity/Q7991381",
            "qid": "Q7991381",
            "text": "what the",
            "method": "TAGME"
        },
        {
            "label": "inflation",
            "url": "http://www.wikidata.org/entity/Q35865",
            "qid": "Q35865",
            "text": "inflation",
            "method": "TAGME"
        }
    ],
    "Top5 answer": [
        {
            "rank": 1,
            "label": "2001-01-01",
            "url": "",
            "qid": ""
        },
        {
            "rank": 2,
            "label": "1988-01-01",
            "url": "",
            "qid": ""
        },
        {
            "rank": 3,
            "label": "+4.9",
            "url": "",
            "qid": ""
        },
        {
            "rank": 4,
            "label": "1993-01-01",
            "url": "",
            "qid": ""
        },
        {
            "rank": 5,
            "label": "2002-01-01",
            "url": "",
            "qid": ""
        }
    ]
}