{
    "Id": 12043,
    "Question": "when did the team who won the 2006 stanley cup finals championship game win the cup",
    "Temporal signal": [
        "No signal"
    ],
    "Temporal question type": [
        "Temp.Ans"
    ],
    "Answer": [
        {
            "AnswerType": "Entity",
            "WikidataQid": "Q3968223",
            "WikidataLabel": "2006 Stanley Cup Finals",
            "WikipediaURL": "https://en.wikipedia.org/wiki/2006_Stanley_Cup_Finals"
        }
    ],
    "Data set": "development",
    "Question truecase": "When did the team who won the 2006 Stanley cup Finals championship game win the cup?",
    "Seed entity": [
        {
            "label": "2006 Stanley Cup Finals",
            "url": "http://www.wikidata.org/entity/Q3968223",
            "qid": "Q3968223",
            "text": "2006 stanley cup finals championship game",
            "method": "ELQ"
        },
        {
            "label": "2006 Stanley Cup Finals",
            "url": "http://www.wikidata.org/entity/Q3968223",
            "qid": "Q3968223",
            "text": "won",
            "method": "TAGME"
        },
        {
            "label": "championship",
            "url": "http://www.wikidata.org/entity/Q1079023",
            "qid": "Q1079023",
            "text": "2006 stanley cup finals",
            "method": "TAGME"
        },
        {
            "label": "Super Bowl",
            "url": "http://www.wikidata.org/entity/Q32096",
            "qid": "Q32096",
            "text": "championship",
            "method": "TAGME"
        },
        {
            "label": "The Who",
            "url": "http://www.wikidata.org/entity/Q93346",
            "qid": "Q93346",
            "text": "who",
            "method": "TAGME"
        },
        {
            "label": "team",
            "url": "http://www.wikidata.org/entity/Q327245",
            "qid": "Q327245",
            "text": "team",
            "method": "TAGME"
        }
    ],
    "Top5 answer": [
        {
            "rank": 1,
            "label": "2006 Stanley Cup Finals",
            "url": "http://www.wikidata.org/entity/Q3968223",
            "qid": "Q3968223"
        },
        {
            "rank": 2,
            "label": "Super Bowl XIII",
            "url": "http://www.wikidata.org/entity/Q632786",
            "qid": "Q632786"
        },
        {
            "rank": 3,
            "label": "Super Bowl XXII",
            "url": "http://www.wikidata.org/entity/Q474760",
            "qid": "Q474760"
        },
        {
            "rank": 4,
            "label": "Super Bowl XXXIX",
            "url": "http://www.wikidata.org/entity/Q926745",
            "qid": "Q926745"
        },
        {
            "rank": 5,
            "label": "Super Bowl VII",
            "url": "http://www.wikidata.org/entity/Q378744",
            "qid": "Q378744"
        }
    ]
}