{
    "Id": 2820,
    "Question": "what is head of state of north korea that is start time is 1948-9-9",
    "Temporal signal": [
        "START"
    ],
    "Temporal question type": [
        "Explicit"
    ],
    "Answer": [
        {
            "AnswerType": "Entity",
            "WikidataQid": "Q41117",
            "WikidataLabel": "Kim Il-sung",
            "WikipediaURL": "https://en.wikipedia.org/wiki/Kim_Il-sung"
        }
    ],
    "Data set": "train",
    "Question truecase": "What is head of state of North Korea that is start time is 1948-9- 9?",
    "Seed entity": [
        {
            "label": "head of state",
            "url": "http://www.wikidata.org/entity/Q48352",
            "qid": "Q48352",
            "text": "head of state",
            "method": "ELQ and TAGME"
        },
        {
            "label": "North Korea",
            "url": "http://www.wikidata.org/entity/Q423",
            "qid": "Q423",
            "text": "north korea",
            "method": "ELQ and TAGME"
        },
        {
            "label": "START I",
            "url": "http://www.wikidata.org/entity/Q931492",
            "qid": "Q931492",
            "text": "start",
            "method": "TAGME"
        },
        {
            "label": "Time",
            "url": "http://www.wikidata.org/entity/Q43297",
            "qid": "Q43297",
            "text": "time",
            "method": "TAGME"
        }
    ],
    "Top5 answer": [
        {
            "rank": 1,
            "label": "Kim Il-sung",
            "url": "http://www.wikidata.org/entity/Q41117",
            "qid": "Q41117"
        },
        {
            "rank": 2,
            "label": "Kim Jong-il",
            "url": "http://www.wikidata.org/entity/Q10665",
            "qid": "Q10665"
        },
        {
            "rank": 3,
            "label": "North Korea",
            "url": "http://www.wikidata.org/entity/Q423",
            "qid": "Q423"
        },
        {
            "rank": 4,
            "label": "Kim Young-sook",
            "url": "http://www.wikidata.org/entity/Q714481",
            "qid": "Q714481"
        },
        {
            "rank": 5,
            "label": "Kim Jong-un",
            "url": "http://www.wikidata.org/entity/Q56226",
            "qid": "Q56226"
        }
    ]
}