{
    "Id": 2831,
    "Question": "when did sydney barnes start playing cricket with the minor counties of english and welsh cricket group",
    "Temporal signal": [
        "No signal"
    ],
    "Temporal question type": [
        "Temp.Ans"
    ],
    "Answer": [
        {
            "AnswerType": "Value",
            "AnswerArgument": "1929-01-01T00:00:00Z"
        }
    ],
    "Data set": "train",
    "Question truecase": "When did Sydney Barnes start playing cricket with the minor counties of English and Welsh cricket group?",
    "Seed entity": [
        {
            "label": "Sydney Barnes",
            "url": "http://www.wikidata.org/entity/Q7659829",
            "qid": "Q7659829",
            "text": "sydney barnes",
            "method": "ELQ and TAGME"
        },
        {
            "label": "Minor counties of English and Welsh cricket",
            "url": "http://www.wikidata.org/entity/Q6869173",
            "qid": "Q6869173",
            "text": "minor counties of english and welsh cricket",
            "method": "TAGME"
        },
        {
            "label": "First Professional Football League",
            "url": "http://www.wikidata.org/entity/Q12837728",
            "qid": "Q12837728",
            "text": "group",
            "method": "TAGME"
        },
        {
            "label": "Start!",
            "url": "http://www.wikidata.org/entity/Q7602459",
            "qid": "Q7602459",
            "text": "start",
            "method": "TAGME"
        }
    ],
    "Top5 answer": [
        {
            "rank": 1,
            "label": "1929-01-01",
            "url": "",
            "qid": ""
        },
        {
            "rank": 2,
            "label": "1930-01-01",
            "url": "",
            "qid": ""
        },
        {
            "rank": 3,
            "label": "1990-01-01",
            "url": "",
            "qid": ""
        },
        {
            "rank": 4,
            "label": "1986-01-01",
            "url": "",
            "qid": ""
        },
        {
            "rank": 5,
            "label": "1903-01-01",
            "url": "",
            "qid": ""
        }
    ]
}