{
    "Id": 3121,
    "Question": "what is the point in time for audra mcdonald has award received as tony award for best featured actress in a play",
    "Temporal signal": [
        "No signal"
    ],
    "Temporal question type": [
        "Temp.Ans"
    ],
    "Answer": [
        {
            "AnswerType": "Value",
            "AnswerArgument": "1996-01-01T00:00:00Z"
        },
        {
            "AnswerType": "Value",
            "AnswerArgument": "2004-01-01T00:00:00Z"
        }
    ],
    "Data set": "train",
    "Question truecase": "What is the point in time for Audra McDonald has award received as Tony award for best featured actress in a play?",
    "Seed entity": [
        {
            "label": "Audra McDonald",
            "url": "http://www.wikidata.org/entity/Q267676",
            "qid": "Q267676",
            "text": "audra mcdonald",
            "method": "ELQ and TAGME"
        },
        {
            "label": "Tony Award for Best Featured Actress in a Play",
            "url": "http://www.wikidata.org/entity/Q627778",
            "qid": "Q627778",
            "text": "tony award for best featured actress in a play",
            "method": "ELQ"
        },
        {
            "label": "Tony Award",
            "url": "http://www.wikidata.org/entity/Q191874",
            "qid": "Q191874",
            "text": "tony award",
            "method": "TAGME"
        },
        {
            "label": "Play",
            "url": "http://www.wikidata.org/entity/Q25379",
            "qid": "Q25379",
            "text": "play",
            "method": "TAGME"
        },
        {
            "label": "time",
            "url": "http://www.wikidata.org/entity/Q11471",
            "qid": "Q11471",
            "text": "point in time",
            "method": "TAGME"
        },
        {
            "label": "Time",
            "url": "http://www.wikidata.org/entity/Q43297",
            "qid": "Q43297",
            "text": "time",
            "method": "TAGME"
        },
        {
            "label": "actor",
            "url": "http://www.wikidata.org/entity/Q33999",
            "qid": "Q33999",
            "text": "actress",
            "method": "TAGME"
        }
    ],
    "Top5 answer": [
        {
            "rank": 1,
            "label": "2004-01-01",
            "url": "",
            "qid": ""
        },
        {
            "rank": 2,
            "label": "2012-01-01",
            "url": "",
            "qid": ""
        },
        {
            "rank": 3,
            "label": "1955-01-01",
            "url": "",
            "qid": ""
        },
        {
            "rank": 4,
            "label": "2014-01-01",
            "url": "",
            "qid": ""
        },
        {
            "rank": 5,
            "label": "2016-01-01",
            "url": "",
            "qid": ""
        }
    ]
}