{
    "Id": 4219,
    "Question": "what is award received of martin buber that is point in time is 1958-1-1",
    "Temporal signal": [
        "OVERLAP"
    ],
    "Temporal question type": [
        "Explicit"
    ],
    "Answer": [
        {
            "AnswerType": "Entity",
            "WikidataQid": "Q1534190",
            "WikidataLabel": "Goethe Plaque of the City of Frankfurt",
            "WikipediaURL": "https://en.wikipedia.org/wiki/Goethe_Plaque_of_the_City_of_Frankfurt"
        }
    ],
    "Data set": "train",
    "Question truecase": "What is award received of Martin Buber that is point in time is 1958-1- 1?",
    "Seed entity": [
        {
            "label": "Martin Buber",
            "url": "http://www.wikidata.org/entity/Q84423",
            "qid": "Q84423",
            "text": "martin buber",
            "method": "ELQ and TAGME"
        },
        {
            "label": "problem of time",
            "url": "http://www.wikidata.org/entity/Q18344764",
            "qid": "Q18344764",
            "text": "point in time",
            "method": "ELQ"
        },
        {
            "label": "Writers Guild of America Award",
            "url": "http://www.wikidata.org/entity/Q1415017",
            "qid": "Q1415017",
            "text": "award",
            "method": "TAGME"
        },
        {
            "label": "time",
            "url": "http://www.wikidata.org/entity/Q11471",
            "qid": "Q11471",
            "text": "point in time",
            "method": "TAGME"
        }
    ],
    "Top5 answer": [
        {
            "rank": 1,
            "label": "Goethe Plaque of the City of Frankfurt",
            "url": "http://www.wikidata.org/entity/Q1534190",
            "qid": "Q1534190"
        },
        {
            "rank": 2,
            "label": "Austrians",
            "url": "http://www.wikidata.org/entity/Q237534",
            "qid": "Q237534"
        },
        {
            "rank": 3,
            "label": "Erasmus Prize",
            "url": "http://www.wikidata.org/entity/Q974780",
            "qid": "Q974780"
        },
        {
            "rank": 4,
            "label": "Friedrich Lehmann",
            "url": "http://www.wikidata.org/entity/Q1460700",
            "qid": "Q1460700"
        },
        {
            "rank": 5,
            "label": "Peace Prize of the German Publishers' Association",
            "url": "http://www.wikidata.org/entity/Q265920",
            "qid": "Q265920"
        }
    ]
}