{
    "Id": 5749,
    "Question": "in 2008, which award did mohamed elbaradei receive",
    "Temporal signal": [
        "OVERLAP"
    ],
    "Temporal question type": [
        "Explicit"
    ],
    "Answer": [
        {
            "AnswerType": "Entity",
            "WikidataQid": "Q3241794",
            "WikidataLabel": "Indira Gandhi Prize",
            "WikipediaURL": "https://en.wikipedia.org/wiki/Indira_Gandhi_Prize"
        }
    ],
    "Data set": "train",
    "Question truecase": "In 2008, which award did Mohamed Elbaradei receive?",
    "Seed entity": [
        {
            "label": "Mohamed ElBaradei",
            "url": "http://www.wikidata.org/entity/Q133308",
            "qid": "Q133308",
            "text": "mohamed elbaradei",
            "method": "ELQ and TAGME"
        },
        {
            "label": "award",
            "url": "http://www.wikidata.org/entity/Q618779",
            "qid": "Q618779",
            "text": "award",
            "method": "TAGME"
        }
    ],
    "Top5 answer": [
        {
            "rank": 1,
            "label": "Indira Gandhi Prize",
            "url": "http://www.wikidata.org/entity/Q3241794",
            "qid": "Q3241794"
        },
        {
            "rank": 2,
            "label": "Intergovernmental Panel on Climate Change",
            "url": "http://www.wikidata.org/entity/Q171183",
            "qid": "Q171183"
        },
        {
            "rank": 3,
            "label": "Al Gore",
            "url": "http://www.wikidata.org/entity/Q19673",
            "qid": "Q19673"
        },
        {
            "rank": 4,
            "label": "Nobel Peace Prize",
            "url": "http://www.wikidata.org/entity/Q35637",
            "qid": "Q35637"
        },
        {
            "rank": 5,
            "label": "Abiy Ahmed",
            "url": "http://www.wikidata.org/entity/Q50365049",
            "qid": "Q50365049"
        }
    ]
}