{
    "Id": 7526,
    "Question": "what is position held of david trimble and elected in",
    "Temporal signal": [
        "No signal"
    ],
    "Temporal question type": [
        "Temp.Ans"
    ],
    "Answer": [
        {
            "AnswerType": "Entity",
            "WikidataQid": "Q2076187",
            "WikidataLabel": "2003 Northern Ireland Assembly election",
            "WikipediaURL": "https://en.wikipedia.org/wiki/2003_Northern_Ireland_Assembly_election"
        },
        {
            "AnswerType": "Entity",
            "WikidataQid": "Q2076208",
            "WikidataLabel": "1998 Northern Ireland Assembly election",
            "WikipediaURL": "https://en.wikipedia.org/wiki/1998_Northern_Ireland_Assembly_election"
        },
        {
            "AnswerType": "Entity",
            "WikidataQid": "Q4593848",
            "WikidataLabel": "1998 New Year Honours",
            "WikipediaURL": "https://en.wikipedia.org/wiki/1998_New_Year_Honours"
        },
        {
            "AnswerType": "Entity",
            "WikidataQid": "Q543609",
            "WikidataLabel": "1992 United Kingdom general election",
            "WikipediaURL": "https://en.wikipedia.org/wiki/1992_United_Kingdom_general_election"
        },
        {
            "AnswerType": "Entity",
            "WikidataQid": "Q590740",
            "WikidataLabel": "2001 United Kingdom general election",
            "WikipediaURL": "https://en.wikipedia.org/wiki/2001_United_Kingdom_general_election"
        },
        {
            "AnswerType": "Entity",
            "WikidataQid": "Q7898476",
            "WikidataLabel": "Upper Bann by-election, 1990",
            "WikipediaURL": "https://en.wikipedia.org/wiki/1990_Upper_Bann_by-election"
        },
        {
            "AnswerType": "Entity",
            "WikidataQid": "Q918503",
            "WikidataLabel": "1997 United Kingdom general election",
            "WikipediaURL": "https://en.wikipedia.org/wiki/1997_United_Kingdom_general_election"
        }
    ],
    "Data set": "train",
    "Question truecase": "What is position held of David Trimble and elected in?",
    "Seed entity": [
        {
            "label": "David Trimble",
            "url": "http://www.wikidata.org/entity/Q192556",
            "qid": "Q192556",
            "text": "david trimble",
            "method": "ELQ and TAGME"
        },
        {
            "label": "1996 Israeli general election",
            "url": "http://www.wikidata.org/entity/Q2917048",
            "qid": "Q2917048",
            "text": "elected",
            "method": "TAGME"
        },
        {
            "label": "association football position",
            "url": "http://www.wikidata.org/entity/Q4611891",
            "qid": "Q4611891",
            "text": "position",
            "method": "TAGME"
        }
    ],
    "Top5 answer": [
        {
            "rank": 1,
            "label": "1992 United Kingdom general election",
            "url": "http://www.wikidata.org/entity/Q543609",
            "qid": "Q543609"
        },
        {
            "rank": 2,
            "label": "1997 United Kingdom general election",
            "url": "http://www.wikidata.org/entity/Q918503",
            "qid": "Q918503"
        },
        {
            "rank": 3,
            "label": "2001 United Kingdom general election",
            "url": "http://www.wikidata.org/entity/Q590740",
            "qid": "Q590740"
        },
        {
            "rank": 4,
            "label": "Upper Bann by-election, 1990",
            "url": "http://www.wikidata.org/entity/Q7898476",
            "qid": "Q7898476"
        },
        {
            "rank": 5,
            "label": "1998 New Year Honours",
            "url": "http://www.wikidata.org/entity/Q4593848",
            "qid": "Q4593848"
        }
    ]
}