{
    "Id": 11153,
    "Question": "when did terry eagleton begin working at the university of manchester",
    "Temporal signal": [
        "No signal"
    ],
    "Type": [
        "Temp.Ans"
    ],
    "Answer": [
        {
            "AnswerType": "Value",
            "AnswerArgument": "2001-01-01T00:00:00Z"
        }
    ],
    "Question truecase": "When did Terry Eagleton begin working at the University of Manchester?",
    "Seed entity": [
        {
            "label": "Terry Eagleton",
            "url": "http://www.wikidata.org/entity/Q315349",
            "qid": "Q315349",
            "text": "terry eagleton",
            "method": "ELQ and TAGME"
        },
        {
            "label": "University of Manchester",
            "url": "http://www.wikidata.org/entity/Q230899",
            "qid": "Q230899",
            "text": "university of manchester",
            "method": "ELQ"
        },
        {
            "label": "University of Oxford",
            "url": "http://www.wikidata.org/entity/Q34433",
            "qid": "Q34433",
            "text": "the university",
            "method": "TAGME"
        },
        {
            "label": "Manchester",
            "url": "http://www.wikidata.org/entity/Q18125",
            "qid": "Q18125",
            "text": "manchester",
            "method": "TAGME"
        }
    ],
    "Top5 answer": [
        {
            "rank": 1,
            "label": "2001-01-01",
            "url": "",
            "qid": ""
        },
        {
            "rank": 2,
            "label": "1969-01-01",
            "url": "",
            "qid": ""
        },
        {
            "rank": 3,
            "label": "2008-01-01",
            "url": "",
            "qid": ""
        },
        {
            "rank": 4,
            "label": "1996-01-01",
            "url": "",
            "qid": ""
        },
        {
            "rank": 5,
            "label": "University of Oxford",
            "url": "http://www.wikidata.org/entity/Q34433",
            "qid": "Q34433"
        }
    ]
}