{
    "Id": 11243,
    "Question": "geneva was declared the capitol of the republic of geneva on what date",
    "Temporal signal": [
        "No signal"
    ],
    "Type": [
        "Temp.Ans"
    ],
    "Answer": [
        {
            "AnswerType": "Value",
            "AnswerArgument": "1815-01-01T00:00:00Z"
        },
        {
            "AnswerType": "Value",
            "AnswerArgument": "1798-01-01T00:00:00Z"
        }
    ],
    "Question truecase": "Geneva was declared the Capitol of the Republic of Geneva on what date?",
    "Seed entity": [
        {
            "label": "capital city",
            "url": "http://www.wikidata.org/entity/Q5119",
            "qid": "Q5119",
            "text": "capitol",
            "method": "ELQ"
        },
        {
            "label": "Canton of Geneva",
            "url": "http://www.wikidata.org/entity/Q11917",
            "qid": "Q11917",
            "text": "republic of geneva",
            "method": "ELQ"
        },
        {
            "label": "Geneva",
            "url": "http://www.wikidata.org/entity/Q71",
            "qid": "Q71",
            "text": "geneva",
            "method": "ELQ and TAGME"
        },
        {
            "label": "United States Capitol",
            "url": "http://www.wikidata.org/entity/Q54109",
            "qid": "Q54109",
            "text": "the capitol",
            "method": "TAGME"
        },
        {
            "label": "Phoenix dactylifera",
            "url": "http://www.wikidata.org/entity/Q25292",
            "qid": "Q25292",
            "text": "date",
            "method": "TAGME"
        },
        {
            "label": "French First Republic",
            "url": "http://www.wikidata.org/entity/Q58296",
            "qid": "Q58296",
            "text": "the republic",
            "method": "TAGME"
        }
    ],
    "Top5 answer": [
        {
            "rank": 1,
            "label": "1798-01-01",
            "url": "",
            "qid": ""
        },
        {
            "rank": 2,
            "label": "1815-01-01",
            "url": "",
            "qid": ""
        },
        {
            "rank": 3,
            "label": "Burning of Washington",
            "url": "http://www.wikidata.org/entity/Q897786",
            "qid": "Q897786"
        },
        {
            "rank": 4,
            "label": "1813-01-01",
            "url": "",
            "qid": ""
        },
        {
            "rank": 5,
            "label": "1890-01-01",
            "url": "",
            "qid": ""
        }
    ]
}