{
    "Id": 14506,
    "Question": "what year did the cleveland indians make it to the world series, where the results were 4-2",
    "Temporal signal": [
        "No signal"
    ],
    "Type": [
        "Temp.Ans"
    ],
    "Answer": [
        {
            "AnswerType": "Entity",
            "WikidataQid": "Q1317331",
            "WikidataLabel": "1997 World Series",
            "WikipediaURL": "https://en.wikipedia.org/wiki/1997_World_Series"
        },
        {
            "AnswerType": "Entity",
            "WikidataQid": "Q636375",
            "WikidataLabel": "1995 World Series",
            "WikipediaURL": "https://en.wikipedia.org/wiki/1995_World_Series"
        },
        {
            "AnswerType": "Entity",
            "WikidataQid": "Q3511282",
            "WikidataLabel": "1920 World Series",
            "WikipediaURL": "https://en.wikipedia.org/wiki/1920_World_Series"
        },
        {
            "AnswerType": "Entity",
            "WikidataQid": "Q3511285",
            "WikidataLabel": "1948 World Series",
            "WikipediaURL": "https://en.wikipedia.org/wiki/1948_World_Series"
        },
        {
            "AnswerType": "Entity",
            "WikidataQid": "Q3511287",
            "WikidataLabel": "1954 World Series",
            "WikipediaURL": "https://en.wikipedia.org/wiki/1954_World_Series"
        }
    ],
    "Question truecase": "What year did the Cleveland Indians make it to the world series, where the results were 4-2?",
    "Seed entity": [
        {
            "label": "World Series",
            "url": "http://www.wikidata.org/entity/Q265538",
            "qid": "Q265538",
            "text": "world series",
            "method": "ELQ"
        },
        {
            "label": "Cleveland Indians",
            "url": "http://www.wikidata.org/entity/Q642553",
            "qid": "Q642553",
            "text": "cleveland indians",
            "method": "ELQ"
        },
        {
            "label": "World Series",
            "url": "http://www.wikidata.org/entity/Q265538",
            "qid": "Q265538",
            "text": "the world series",
            "method": "TAGME"
        },
        {
            "label": "1954 Cleveland Indians season",
            "url": "http://www.wikidata.org/entity/Q4568041",
            "qid": "Q4568041",
            "text": "the cleveland indians",
            "method": "TAGME"
        },
        {
            "label": "Baseball Hall of Fame balloting, 2013",
            "url": "http://www.wikidata.org/entity/Q4866532",
            "qid": "Q4866532",
            "text": "the results",
            "method": "TAGME"
        },
        {
            "label": "1976 World Series",
            "url": "http://www.wikidata.org/entity/Q4295898",
            "qid": "Q4295898",
            "text": "year",
            "method": "TAGME"
        }
    ],
    "Top5 answer": [
        {
            "rank": 1,
            "label": "2010 World Series",
            "url": "http://www.wikidata.org/entity/Q928040",
            "qid": "Q928040"
        },
        {
            "rank": 2,
            "label": "2014 World Series",
            "url": "http://www.wikidata.org/entity/Q17514457",
            "qid": "Q17514457"
        },
        {
            "rank": 3,
            "label": "2004 World Series",
            "url": "http://www.wikidata.org/entity/Q1341797",
            "qid": "Q1341797"
        },
        {
            "rank": 4,
            "label": "2012 World Series",
            "url": "http://www.wikidata.org/entity/Q1190373",
            "qid": "Q1190373"
        },
        {
            "rank": 5,
            "label": "1997 World Series",
            "url": "http://www.wikidata.org/entity/Q1317331",
            "qid": "Q1317331"
        }
    ]
}