{
    "Id": 15329,
    "Question": "who was the president in 1980 of the nation that uses the pakistani repuu as money",
    "Temporal signal": [
        "OVERLAP"
    ],
    "Type": [
        "Explicit"
    ],
    "Answer": [
        {
            "AnswerType": "Entity",
            "WikidataQid": "Q200499",
            "WikidataLabel": "Muhammad Zia-ul-Haq",
            "WikipediaURL": "https://en.wikipedia.org/wiki/Muhammad_Zia-ul-Haq"
        }
    ],
    "Question truecase": "Who was the President in 1980 of the nation that uses the Pakistani Repuu as money?",
    "Seed entity": [
        {
            "label": "Pakistani rupee",
            "url": "http://www.wikidata.org/entity/Q188289",
            "qid": "Q188289",
            "text": "pakistani repuu",
            "method": "ELQ"
        },
        {
            "label": "President of Pakistan",
            "url": "http://www.wikidata.org/entity/Q473984",
            "qid": "Q473984",
            "text": "president",
            "method": "ELQ"
        },
        {
            "label": "President of the United States",
            "url": "http://www.wikidata.org/entity/Q11696",
            "qid": "Q11696",
            "text": "the president",
            "method": "TAGME"
        },
        {
            "label": "The Nation",
            "url": "http://www.wikidata.org/entity/Q1897630",
            "qid": "Q1897630",
            "text": "the nation",
            "method": "TAGME"
        },
        {
            "label": "money",
            "url": "http://www.wikidata.org/entity/Q1368",
            "qid": "Q1368",
            "text": "money",
            "method": "TAGME"
        }
    ],
    "Top5 answer": [
        {
            "rank": 1,
            "label": "Muhammad Zia-ul-Haq",
            "url": "http://www.wikidata.org/entity/Q200499",
            "qid": "Q200499"
        },
        {
            "rank": 2,
            "label": "Lyndon B. Johnson",
            "url": "http://www.wikidata.org/entity/Q9640",
            "qid": "Q9640"
        },
        {
            "rank": 3,
            "label": "Richard Nixon",
            "url": "http://www.wikidata.org/entity/Q9588",
            "qid": "Q9588"
        },
        {
            "rank": 4,
            "label": "John F. Kennedy",
            "url": "http://www.wikidata.org/entity/Q9696",
            "qid": "Q9696"
        },
        {
            "rank": 5,
            "label": "Ghulam Ishaq Khan",
            "url": "http://www.wikidata.org/entity/Q314776",
            "qid": "Q314776"
        }
    ]
}