{
    "Id": 6262,
    "Question": "what award did john wayne receive in 2007",
    "Temporal signal": [
        "OVERLAP"
    ],
    "Type": [
        "Explicit"
    ],
    "Answer": [
        {
            "AnswerType": "Entity",
            "WikidataQid": "Q5020532",
            "WikidataLabel": "California Hall of Fame",
            "WikipediaURL": "https://en.wikipedia.org/wiki/California_Hall_of_Fame"
        }
    ],
    "Question truecase": "What award did John Wayne receive in 2007?",
    "Seed entity": [
        {
            "label": "John Wayne",
            "url": "http://www.wikidata.org/entity/Q40531",
            "qid": "Q40531",
            "text": "john wayne",
            "method": "ELQ and TAGME"
        },
        {
            "label": "award",
            "url": "http://www.wikidata.org/entity/Q618779",
            "qid": "Q618779",
            "text": "award",
            "method": "TAGME"
        }
    ],
    "Top5 answer": [
        {
            "rank": 1,
            "label": "California Hall of Fame",
            "url": "http://www.wikidata.org/entity/Q5020532",
            "qid": "Q5020532"
        },
        {
            "rank": 2,
            "label": "Academy Award for Best Actor",
            "url": "http://www.wikidata.org/entity/Q103916",
            "qid": "Q103916"
        },
        {
            "rank": 3,
            "label": "Academy Award for Best Picture",
            "url": "http://www.wikidata.org/entity/Q102427",
            "qid": "Q102427"
        },
        {
            "rank": 4,
            "label": "Gary Becker",
            "url": "http://www.wikidata.org/entity/Q191020",
            "qid": "Q191020"
        },
        {
            "rank": 5,
            "label": "John Wayne",
            "url": "http://www.wikidata.org/entity/Q40531",
            "qid": "Q40531"
        }
    ]
}