{
    "Id": 7966,
    "Question": "what is twinned administrative body of chihuahua that is start time is 2008-3-10",
    "Temporal signal": [
        "START"
    ],
    "Type": [
        "Explicit"
    ],
    "Answer": [
        {
            "AnswerType": "Entity",
            "WikidataQid": "Q34804",
            "WikidataLabel": "Albuquerque",
            "WikipediaURL": "https://en.wikipedia.org/wiki/Albuquerque,_New_Mexico"
        }
    ],
    "Question truecase": "What is twinned administrative body of Chihuahua that is start time is 2008-3- 10?",
    "Seed entity": [
        {
            "label": "twin town",
            "url": "http://www.wikidata.org/entity/Q184711",
            "qid": "Q184711",
            "text": "twinned",
            "method": "ELQ"
        },
        {
            "label": "Chihuahua",
            "url": "http://www.wikidata.org/entity/Q655",
            "qid": "Q655",
            "text": "chihuahua",
            "method": "ELQ and TAGME"
        },
        {
            "label": "Starting Time",
            "url": "http://www.wikidata.org/entity/Q7602590",
            "qid": "Q7602590",
            "text": "start time",
            "method": "TAGME"
        },
        {
            "label": "Business economics",
            "url": "http://www.wikidata.org/entity/Q2043282",
            "qid": "Q2043282",
            "text": "administrative body",
            "method": "TAGME"
        }
    ],
    "Top5 answer": [
        {
            "rank": 1,
            "label": "Albuquerque",
            "url": "http://www.wikidata.org/entity/Q34804",
            "qid": "Q34804"
        },
        {
            "rank": 2,
            "label": "Chihuahua",
            "url": "http://www.wikidata.org/entity/Q61302",
            "qid": "Q61302"
        },
        {
            "rank": 3,
            "label": "Chihuahua Municipality",
            "url": "http://www.wikidata.org/entity/Q2475171",
            "qid": "Q2475171"
        },
        {
            "rank": 4,
            "label": "Texas",
            "url": "http://www.wikidata.org/entity/Q1439",
            "qid": "Q1439"
        },
        {
            "rank": 5,
            "label": "El Paso",
            "url": "http://www.wikidata.org/entity/Q16562",
            "qid": "Q16562"
        }
    ]
}