{
    "Id": 8785,
    "Question": "what part of somogy county came to an end in the year 1989 which was located in the administrative territorial entity",
    "Temporal signal": [
        "FINISH"
    ],
    "Type": [
        "Explicit"
    ],
    "Answer": [
        {
            "AnswerType": "Entity",
            "WikidataQid": "Q16410",
            "WikidataLabel": "People's Republic of Hungary",
            "WikipediaURL": "https://en.wikipedia.org/wiki/Hungarian_People%27s_Republic"
        }
    ],
    "Question truecase": "What part of Somogy County came to an end in the year 1989 which was located in the administrative territorial entity?",
    "Seed entity": [
        {
            "label": "Somogy County",
            "url": "http://www.wikidata.org/entity/Q190522",
            "qid": "Q190522",
            "text": "somogy county",
            "method": "ELQ and TAGME"
        },
        {
            "label": "constituent part of the United Kingdom",
            "url": "http://www.wikidata.org/entity/Q3336843",
            "qid": "Q3336843",
            "text": "part",
            "method": "TAGME"
        },
        {
            "label": "Jewish eschatology",
            "url": "http://www.wikidata.org/entity/Q2411408",
            "qid": "Q2411408",
            "text": "an end",
            "method": "TAGME"
        },
        {
            "label": "year",
            "url": "http://www.wikidata.org/entity/Q577",
            "qid": "Q577",
            "text": "the year",
            "method": "TAGME"
        }
    ],
    "Top5 answer": [
        {
            "rank": 1,
            "label": "People's Republic of Hungary",
            "url": "http://www.wikidata.org/entity/Q16410",
            "qid": "Q16410"
        },
        {
            "rank": 2,
            "label": "Somogy County",
            "url": "http://www.wikidata.org/entity/Q190522",
            "qid": "Q190522"
        },
        {
            "rank": 3,
            "label": "Hungary",
            "url": "http://www.wikidata.org/entity/Q28",
            "qid": "Q28"
        },
        {
            "rank": 4,
            "label": "Siófok District",
            "url": "http://www.wikidata.org/entity/Q853254",
            "qid": "Q853254"
        },
        {
            "rank": 5,
            "label": "Southern Transdanubia",
            "url": "http://www.wikidata.org/entity/Q781747",
            "qid": "Q781747"
        }
    ]
}